{"name":"Towing a Comet","id":"75","cost":23,"card_type":"Event","deck":"Basic","requirements":{"global":{"min_temperature":-30,"max_temperature":8,"min_oxygen":0,"max_oxygen":14,"min_ocean":0,"max_ocean":9},"local":[]},"tags":["Space","Event"],"production":[{"MegaCredits":0},{"Steel":0},{"Titanium":0},{"Plants":0},{"Energy":0},{"Heat":0}],"resources":[{"MegaCredits":0},{"Steel":0},{"Titanium":0},{"Plants":2},{"Energy":0},{"Heat":0}],"resources_on_card":"None","terraforming_effect":{"temperature":{"Number":0},"oxygen":{"Number":1},"ocean":{"Number":1},"tr":{"Number":0},"vp":{"Number":0}},"interactions":{"tile_placement":"Ref","num_actions_or_effect":{"Number":0},"depends_on_opponents":"No","affects_opponents":"No","holds_resources":"None"},"text":{"action_or_ongoing_effect_text":"","onetime_effect_text":"Gain 2 plants. Raise oxygen level 1 step and place an ocean tile."}}